LICENSE
MANIFEST.in
README.md
requirements.txt
setup.py
multiego/__init__.py
multiego/base_ego.py
multiego/base_multiplyego.py
multiego/ego.py
multiego/multiplyego.py
multiego.egg-info/PKG-INFO
multiego.egg-info/SOURCES.txt
multiego.egg-info/dependency_links.txt
multiego.egg-info/requires.txt
multiego.egg-info/top_level.txt
test/test_base_ego.py
test/test_multiego.py